{"type": "facebook messenger for allevents bot", "people": [{"count": 1, "city": "mumbai", "country": "IN", "userid": "101", "state": "MH", "longitude": -1, "flag": "", "latitude": -2, "generated": "True", "search_tag": "football"}, {"count": 36, "city": "Bangalore", "country": "IN", "userid": "104", "state": "KA", "longitude": 77.5945627, "generated": "False", "latitude": 12.9715987, "flag": "", "search_tag": "sports"}, {"count": 33, "city": "Andheri ", "country": "", "userid": "102", "generated": "False", "longitude": 72.8697339, "state": "", "latitude": 19.113645, "flag": "", "search_tag": "business"}]}